noLZSS/__init__.py
noLZSS/core.py
noLZSS/_noLZSS.cpython-39-darwin.so
noLZSS/utils.py
noLZSS/parallel.py
noLZSS/genomics/sequences.py
noLZSS/genomics/lsf_batch_factorize.py
noLZSS/genomics/__init__.py
noLZSS/genomics/plots.py
noLZSS/genomics/batch_factorize.py
noLZSS/genomics/fasta.py
nolzss-1.1.0.dist-info/RECORD
nolzss-1.1.0.dist-info/WHEEL
nolzss-1.1.0.dist-info/METADATA
nolzss-1.1.0.dist-info/licenses/LICENSE
