Metadata-Version: 2.2
Name: noLZSS
Version: 1.1.0
Summary: Non-overlapping Lempel-Ziv-Storer-Szymanski factorization (high-performance C++ core with Python bindings)
Author: Omer Kerner
License: BSD-3-Clause
Classifier: Programming Language :: Python :: 3
Classifier: Programming Language :: C++
Classifier: License :: OSI Approved :: BSD License
Classifier: Operating System :: OS Independent
Classifier: Topic :: Software Development :: Libraries :: Python Modules
Classifier: Intended Audience :: Science/Research
Project-URL: Homepage, https://github.com/OmerKerner/noLZSS
Requires-Python: >=3.8
Provides-Extra: benchmark
Requires-Dist: matplotlib>=3.5.0; extra == "benchmark"
Provides-Extra: plotting
Requires-Dist: matplotlib>=3.5.0; extra == "plotting"
Provides-Extra: panel
Requires-Dist: numpy>=1.20.0; extra == "panel"
Requires-Dist: pandas>=1.3.0; extra == "panel"
Requires-Dist: holoviews>=1.15.0; extra == "panel"
Requires-Dist: bokeh>=2.4.0; extra == "panel"
Requires-Dist: panel>=1.0.0; extra == "panel"
Requires-Dist: datashader>=0.14.0; extra == "panel"
Requires-Dist: colorcet>=3.0.0; extra == "panel"
